webread_mcp/__init__.py
webread_mcp/__main__.py
webread_mcp/server.py
webread_mcp-1.0.4.dist-info/METADATA
webread_mcp-1.0.4.dist-info/WHEEL
webread_mcp-1.0.4.dist-info/entry_points.txt
webread_mcp-1.0.4.dist-info/licenses/LICENSE
webread_mcp-1.0.4.dist-info/RECORD
