Metadata-Version: 2.4
Name: webread-mcp
Version: 1.0.4
Summary: MCP server for reading webpages and web search
Project-URL: Homepage, https://hashnode.programmersdiary.com/
Project-URL: Repository, https://github.com/EvalVis/webreadmcp
Author-email: Your Name <your@email.com>
License-Expression: MIT
License-File: LICENSE
Keywords: ai,mcp,model-context-protocol,python,search,website-scraper
Classifier: Intended Audience :: Developers
Classifier: License :: OSI Approved :: MIT License
Classifier: Programming Language :: Python :: 3
Classifier: Programming Language :: Python :: 3.10
Classifier: Programming Language :: Python :: 3.11
Classifier: Programming Language :: Python :: 3.12
Requires-Python: >=3.10
Requires-Dist: beautifulsoup4>=4.14.3
Requires-Dist: duckduckgo-search>=8.1.1
Requires-Dist: httpx>=0.28.1
Requires-Dist: mcp>=1.25.0
